epys/__init__.py
epys/dengeleme_guc_piyasasi.py
epys/dengesizlik_uzlastirma.py
epys/market.py
epys/ortak.py
epys/pre_uzlastirma.py
epys/yekdem_uzlastirma.py
epys_data-1.0.0.dist-info/LICENSE
epys_data-1.0.0.dist-info/METADATA
epys_data-1.0.0.dist-info/WHEEL
epys_data-1.0.0.dist-info/top_level.txt
epys_data-1.0.0.dist-info/RECORD
